mars_datetime-1.0.2.dist-info/licenses/LICENSE.txt
mars_time/__init__.py
mars_time/constants.py
mars_time/orbit.py
mars_time/retimers.py
mars_datetime-1.0.2.dist-info/METADATA
mars_datetime-1.0.2.dist-info/WHEEL
mars_datetime-1.0.2.dist-info/top_level.txt
mars_datetime-1.0.2.dist-info/RECORD
