Metadata-Version: 2.4
Name: mars-datetime
Version: 1.0.2
Summary: Convert between Earth times and Mars times.
Requires-Python: >=3.9
License-File: LICENSE.txt
Requires-Dist: click>=8.1.7
Requires-Dist: numpy>=2.0.2
Requires-Dist: scipy>=1.13.1
Provides-Extra: dev
Requires-Dist: pydata-sphinx-theme>=0.16.1; extra == "dev"
Requires-Dist: pylint>=3.3.7; extra == "dev"
Requires-Dist: pytest>=8.4.1; extra == "dev"
Requires-Dist: sphinx>=7.4.7; extra == "dev"
Dynamic: license-file
